{
 "sn22.133:0.1": "Связанные Наставления 22.133",
 "sn22.133:0.2": "Глава Авидджа",
 "sn22.133:0.3": "Сутта Коттхика",
 "sn22.133:1.1": "В Варанаси в Оленьем Парке в Исипатане.",
 "sn22.133:1.2": "Тогда уважаемый Сарипутта ранним вечером…",
 "sn22.133:1.3": "Сев рядом уважаемый Сарипутта уважаемому Махакоттхике так сказал:",
 "sn22.133:1.4": "««Невежество, невежество», Коттхика товарищ, – так говорят.",
 "sn22.133:1.5": "Что такое, товарищ, невежество",
 "sn22.133:1.6": "и каким образом человек погружён в невежество?»",
 "sn22.133:2.1": "«Друг, вот необученный заурядный человек не понимает в соответствии с действительностью привлекательности, опасности, и спасения в отношении формы…",
 "sn22.133:2.2": "чувства…",
 "sn22.133:2.3": "восприятия…",
 "sn22.133:2.4": "отождествлений…",
 "sn22.133:2.5": "сознания.",
 "sn22.133:2.6": "Это, друг, называется невежеством",
 "sn22.133:2.7": "и таким образом человек погружён в невежество».",
 "sn22.133:3.1": "На так сказанное уважаемый Сарипутта уважаемому Махакоттхике так сказал:",
 "sn22.133:3.2": "««Знание, знание», Коттхика товарищ, – так говорят.",
 "sn22.133:3.3": "Что такое, товарищ, знание",
 "sn22.133:3.4": "и каким образом человек пришёл к истинному знанию?»",
 "sn22.133:4.1": "«Друг, вот обученный ученик Благородных понимает в соответствии с действительностью привлекательность, опасность, и спасение в отношении формы…",
 "sn22.133:4.2": "чувства…",
 "sn22.133:4.3": "восприятия…",
 "sn22.133:4.4": "отождествлений…",
 "sn22.133:4.5": "сознания…",
 "sn22.133:4.6": "Это, друг, называется знанием,",
 "sn22.133:4.7": "и таким образом человек пришёл к знанию».",
 "sn22.133:4.8": "Восьмая."
}