{	
"sn34.7:0.1":	"สํยุตฺต นิกาย ๓๔ฯ๗ ",
"sn34.7:0.2":	"๑ฯ ฌานวคฺค ",
"sn34.7:0.3":	"สมาธิมูลกอภินีหารสุตฺต ",
"sn34.7:1.1":	"สาวตฺถินิทานํฯ ",
"sn34.7:1.2":	"“จตฺตาโรเม, ภิกฺขเว, ฌายีฯ ",
"sn34.7:1.3":	"กตเม จตฺตาโร? ",
"sn34.7:1.4":	"อิธ, ภิกฺขเว, เอกจฺโจ ฌายี สมาธิสฺมึ สมาธิกุสโล โหติ, น สมาธิสฺมึ อภินีหารกุสโลฯ ",
"sn34.7:1.5":	"อิธ ปน, ภิกฺขเว, เอกจฺโจ ฌายี สมาธิสฺมึ อภินีหารกุสโล โหติ, น สมาธิสฺมึ สมาธิกุสโลฯ ",
"sn34.7:1.6":	"อิธ ปน, ภิกฺขเว, เอกจฺโจ ฌายี เนว สมาธิสฺมึ สมาธิกุสโล โหติ, น จ สมาธิสฺมึ อภินีหารกุสโลฯ ",
"sn34.7:1.7":	"อิธ ปน, ภิกฺขเว, เอกจฺโจ ฌายี สมาธิสฺมึ สมาธิกุสโล จ โหติ, สมาธิสฺมึ อภินีหารกุสโล จฯ ",
"sn34.7:1.8":	"ตตฺร, ภิกฺขเว, ยฺวายํ ฌายี สมาธิสฺมึ สมาธิกุสโล จ โหติ สมาธิสฺมึ อภินีหารกุสโล จ อยํ อิเมสํ จตุนฺนํ ฌายีนํ อคฺโค จ เสฏฺโฐ จ โมกฺโข จ อุตฺตโม จ ปวโร จฯ ",
"sn34.7:1.9":	"เสยฺยถาปิ, ภิกฺขเว, ควา ขีรํ …เป… ",
"sn34.7:1.10":	"ปวโร จา”ติฯ ",
"sn34.7:1.11":	"สตฺตมํฯ "
}	
