{	
"sn46.175-184:0.1":	"संयुत्त निकाय ४६।१७५–१८४ ",
"sn46.175-184:0.2":	"१८। पुनओघवग्ग ",
"sn46.175-184:0.3":	"पुनओघादिसुत्त ",
"sn46.175-184:1.1":	"…पे… ",
"sn46.175-184:1.2":	"बोज्झङ्गसंयुत्तस्स पुनओघवग्गो अट्ठारसमो। ",
"sn46.175-184:2.0":	"उद्दानं ",
"sn46.175-184:2.1":	"ओघो योगो उपादानं, ",
"sn46.175-184:2.2":	"गन्था अनुसयेन च; ",
"sn46.175-184:2.3":	"कामगुणा नीवरणा, ",
"sn46.175-184:2.4":	"खन्धा ओरुद्धम्भागियानीति। ",
"sn46.175-184:3.1":	"(रागविनयपरियोसान-दोसविनयपरियोसान-मोहविनयपरियोसानवग्गो वित्थारेतब्बो।) ",
"sn46.175-184:3.2":	"(यदपि मग्गसंयुत्तं वित्थारेतब्बं, तदपि बोज्झङ्गसंयुत्तं वित्थारेतब्बं।) ",
"sn46.175-184:3.3":	"बोज्झङ्गसंयुत्तं दुतियं। "
}	
