{
  "an5.230:0.1": "Восходящие Наставления 5.230",
  "an5.230:0.2": "Глава Андхакавинда",
  "an5.230:0.3": "Сутта Змея Вторая",
  "an5.230:1.1": "“Монахи, есть эти пять опасностей в чёрной змее.",
  "an5.230:1.2": "Какие пять?",
  "an5.230:1.3": "Она гневная, враждебная, смертельно ядовитая, с раздвоенным языком, предаёт друзей.",
  "an5.230:1.4": "Таковы пять опасностей в чёрной змее.",
  "an5.230:2.1": "Точно также, есть эти пять опасностей в женщине.",
  "an5.230:2.2": "Какие пять?",
  "an5.230:2.3": "Она гневная, враждебная, смертельно ядовитая, с раздвоенным языком, предаёт друзей.",
  "an5.230:2.4": "Монахи, вот каким образом женщина смертельно ядовита:",
  "an5.230:2.5": "по большей части женщина склонна к сильной страсти.",
  "an5.230:2.6": "Вот каким образом женщина имеет раздвоенный язык:",
  "an5.230:2.7": "по большей части своими речами она сеет распри.",
  "an5.230:2.8": "Вот каким образом женщина предаёт друзей:",
  "an5.230:2.9": "по большей части она нарушают супружескую верность.",
  "an5.230:2.10": "Таковы пять опасностей в женщинах”.",
  "an5.230:2.11": "Десятая.",
  "an5.230:2.12": "Глава Дигхачарика Третья.",
  "an5.230:3.0": "Оглавление",
  "an5.230:3.1": "",
  "an5.230:3.2": "",
  "an5.230:3.3": "",
  "an5.230:3.4": ""
}